{
  "Layout": "form",
  "Actions": [
    {
      "Id": "file_compare.text",
      "Tooltip": [
        "xP56file_compareK",
        "Click to process your data"
      ],
      "Label": [
        "xIPfile_compare",
        "Get file_compare"
      ],
      "CallFuncList": [
        "xfile_compare.ConvertText"
      ]
    }
  ],
  "Info": {
    "Id": "file_compare",
    "Label": [
      "x41efile_compare",
      "file_compare"
    ],
    "Description": [
      "6wfile_compare",
      "TBC"
    ]
  }
}